test2va/__init__.py
test2va/mod.py
test2va/__pycache__/__init__.cpython-312.pyc
test2va/bridge/__init__.py
test2va/bridge/appium.py
test2va/bridge/check_file_exists.py
test2va/bridge/examples.py
test2va/bridge/post_install.py
test2va/bridge/profile.py
test2va/bridge/stats.py
test2va/bridge/tool.py
test2va/bridge/util.py
test2va/bridge/__pycache__/__init__.cpython-312.pyc
test2va/bridge/__pycache__/appium.cpython-312.pyc
test2va/bridge/__pycache__/post_install.cpython-312.pyc
test2va/bridge/__pycache__/profile.cpython-312.pyc
test2va/bridge/__pycache__/stats.cpython-312.pyc
test2va/bridge/__pycache__/tool.cpython-312.pyc
test2va/bridge/__pycache__/util.cpython-312.pyc
test2va/commands/__init__.py
test2va/commands/cap.py
test2va/commands/example-run.py
test2va/commands/examples.py
test2va/commands/gui.py
test2va/commands/profile.py
test2va/commands/run.py
test2va/commands/stats.py
test2va/commands/__pycache__/__init__.cpython-312.pyc
test2va/commands/__pycache__/cap.cpython-312.pyc
test2va/commands/__pycache__/gui.cpython-312.pyc
test2va/commands/__pycache__/profile.cpython-312.pyc
test2va/commands/__pycache__/run.cpython-312.pyc
test2va/commands/__pycache__/stats.cpython-312.pyc
test2va/const/__init__.py
test2va/const/const.py
test2va/const/__pycache__/__init__.cpython-312.pyc
test2va/const/__pycache__/const.cpython-312.pyc
test2va/examples/Support.java
test2va/examples/BROCCOLI/AccessSupportPageTest.java
test2va/examples/BROCCOLI/AddCategoryTest.java
test2va/examples/BROCCOLI/AddRecipeTest.java
test2va/examples/BROCCOLI/AddRecipeWithDetailsTest.java
test2va/examples/BROCCOLI/ConfigureSeasonalCalendarTest.java
test2va/examples/BROCCOLI/DeleteRecipeTest.java
test2va/examples/BROCCOLI/EditRecipeIngredientsTest.java
test2va/examples/BROCCOLI/LikeRecipeTest.java
test2va/examples/BROCCOLI/SearchRecipeTest.java
test2va/examples/BROCCOLI/SetRegionTest.java
test2va/examples/BROCCOLI/broccoli-1.2.12-fdroid-release.apk
test2va/examples/CALENDER/AddEventTypeTest.java
test2va-1.1.9.dist-info/LICENSE
test2va-1.1.9.dist-info/METADATA
test2va-1.1.9.dist-info/WHEEL
test2va-1.1.9.dist-info/entry_points.txt
test2va-1.1.9.dist-info/top_level.txt
test2va-1.1.9.dist-info/RECORD
