Metadata-Version: 2.1
Name: test2va
Version: 1.1.9
Summary: Test2VA
Author: Anon
License: MIT
Requires-Python: >=3.12
License-File: LICENSE
Requires-Dist: appium-python-client
Requires-Dist: pillow
Requires-Dist: customtkinter
Requires-Dist: openai
Requires-Dist: pydantic
Requires-Dist: lxml
